Metadata-Version: 1.1
Name: GTquant
Version: 0.0.1
Summary: GT strategy backtesting framework
Home-page: http://www.gfedu.cn/class/aqf/
Author: GTedu
Author-email: hans_wang@outlook.com
License: UNKNOWN
Platform: UNKNOWN
Classifier: Programming Language :: Python :: 3
Classifier: License :: OSI Approved :: MIT License
Classifier: Operating System :: Microsoft
